{
  "packages": [
    {
      "name": "UniBIRD",
      "maintainer": "Ionitive Infotronix Pvt.Ltd",
      "websiteURL": "https://github.com/Geeta16-97/UniBIRD",
      "platforms": [
        {
          "name": "UniBIRD",
          "architecture": "esp8266",
          "version": "1.0.0",
          "boards": [
            {"name": "UniBIRD"}
          ],
          "url": "https://geeta16-97.github.io/UniBIRD/releases/UniBIRD-1.0.0.zip",
          "archiveFileName": "UniBIRD-1.0.0.zip",
          "checksum": "SHA-256:958BF6DBBAA1A6152FD224B5E1A59AAFD471834F2E5C705B922D5E9234D47FD8"
        }
      ]
    }
  ]
}